pyopencl/__init__.py
pyopencl/_cl.cpython-314-aarch64-linux-musl.so
pyopencl/_cl.pyi
pyopencl/_cluda.py
pyopencl/_monkeypatch.py
pyopencl/_mymako.py
pyopencl/algorithm.py
pyopencl/array.py
pyopencl/bitonic_sort.py
pyopencl/bitonic_sort_templates.py
pyopencl/cache.py
pyopencl/capture_call.py
pyopencl/clmath.py
pyopencl/clrandom.py
pyopencl/cltypes.py
pyopencl/elementwise.py
pyopencl/invoker.py
pyopencl/ipython_ext.py
pyopencl/py.typed
pyopencl/reduction.py
pyopencl/scan.py
pyopencl/tools.py
pyopencl/typing.py
pyopencl/version.py
pyopencl/.libs/libOpenCL-fd701e27.so.1.0.0
pyopencl/characterize/__init__.py
pyopencl/characterize/performance.py
pyopencl/cl/pyopencl-airy.cl
pyopencl/cl/pyopencl-bessel-j-complex.cl
pyopencl/cl/pyopencl-bessel-j.cl
pyopencl/cl/pyopencl-bessel-y.cl
pyopencl/cl/pyopencl-complex.h
pyopencl/cl/pyopencl-eval-tbl.cl
pyopencl/cl/pyopencl-hankel-complex.cl
pyopencl/cl/pyopencl-random123/array.h
pyopencl/cl/pyopencl-random123/openclfeatures.h
pyopencl/cl/pyopencl-random123/philox.cl
pyopencl/cl/pyopencl-random123/threefry.cl
pyopencl/compyte/.gitignore
pyopencl/compyte/__init__.py
pyopencl/compyte/array.py
pyopencl/compyte/dtypes.py
pyopencl/compyte/pyproject.toml
pyopencl-2026.1.1.dist-info/METADATA
pyopencl-2026.1.1.dist-info/WHEEL
pyopencl-2026.1.1.dist-info/RECORD
pyopencl-2026.1.1.dist-info/licenses/LICENSE
