Metadata-Version: 2.4
Name: pyopencl
Version: 2026.1.1
Summary: Python wrapper for OpenCL
Author-Email: Andreas Kloeckner <inform@tiker.net>
License-Expression: MIT
Classifier: Development Status :: 5 - Production/Stable
Classifier: Environment :: Console
Classifier: Intended Audience :: Developers
Classifier: Intended Audience :: Other Audience
Classifier: Intended Audience :: Science/Research
Classifier: Natural Language :: English
Classifier: Programming Language :: C++
Classifier: Programming Language :: Python
Classifier: Programming Language :: Python :: 3 :: Only
Classifier: Topic :: Scientific/Engineering
Classifier: Topic :: Scientific/Engineering :: Mathematics
Classifier: Topic :: Scientific/Engineering :: Physics
Project-URL: Documentation, https://documen.tician.de/pyopencl
Project-URL: Homepage, https://mathema.tician.de/software/pyopencl
Project-URL: Repository, https://github.com/inducer/pyopencl
Requires-Python: ~=3.10
Requires-Dist: importlib-resources; python_version < "3.9"
Requires-Dist: numpy
Requires-Dist: platformdirs>=2.2
Requires-Dist: pytools>=2025.1.6
Requires-Dist: typing_extensions>=4.6
Provides-Extra: oclgrind
Requires-Dist: oclgrind-binary-distribution>=18.3; extra == "oclgrind"
Provides-Extra: pocl
Requires-Dist: pocl-binary-distribution>=1.2; extra == "pocl"
Provides-Extra: test
Requires-Dist: basedpyright; extra == "test"
Requires-Dist: mako; extra == "test"
Requires-Dist: pytest>=7; extra == "test"
Requires-Dist: ruff; extra == "test"
